{"N": 72, "K": 12, "nTrials": 1000, "nBad": 5, "repairType": "A-X", "defectType": "singledefect", "defectLocation": [0], "ler": 0.0003855058138035883, "perr": 0.01, "d": 6, "type": "z", "time": "2024-07-16T12:15:42.993832"}
{"N": 72, "K": 12, "nTrials": 1000, "nBad": 5, "repairType": "A-X", "defectType": "singledefect", "defectLocation": [0], "ler": 0.0003855058138035883, "perr": 0.02, "d": 5, "type": "z", "time": "2024-07-16T12:15:42.993832"}
{"N": 72, "K": 12, "nTrials": 1000, "nBad": 33, "repairType": "A-X", "defectType": "singledefect", "defectLocation": [0], "ler": 0.0025779623736639223, "perr": 0.03, "d": 5, "type": "z", "time": "2024-07-16T12:15:42.993832"}
{"N": 72, "K": 12, "nTrials": 1000, "nBad": 78, "repairType": "A-X", "defectType": "singledefect", "defectLocation": [0], "ler": 0.006227455856574693, "perr": 0.04, "d": 5, "type": "z", "time": "2024-07-16T12:15:42.993832"}
{"N": 72, "K": 12, "nTrials": 1000, "nBad": 151, "repairType": "A-X", "defectType": "singledefect", "defectLocation": [0], "ler": 0.012513059523785564, "perr": 0.05, "d": 5, "type": "z", "time": "2024-07-16T12:15:42.993832"}
{"N": 72, "K": 12, "nTrials": 1000, "nBad": 236, "repairType": "A-X", "defectType": "singledefect", "defectLocation": [0], "ler": 0.020493817756805477, "perr": 0.06, "d": 5, "type": "z", "time": "2024-07-16T12:15:42.993832"}
{"N": 72, "K": 12, "nTrials": 1000, "nBad": 356, "repairType": "A-X", "defectType": "singledefect", "defectLocation": [0], "ler": 0.03328398605259286, "perr": 0.07, "d": 5, "type": "z", "time": "2024-07-16T12:15:42.993832"}
{"N": 72, "K": 12, "nTrials": 1000, "nBad": 435, "repairType": "A-X", "defectType": "singledefect", "defectLocation": [0], "ler": 0.04296724132612295, "perr": 0.08, "d": 5, "type": "z", "time": "2024-07-16T12:15:42.993832"}
{"N": 72, "K": 12, "nTrials": 1000, "nBad": 558, "repairType": "A-X", "defectType": "singledefect", "defectLocation": [0], "ler": 0.06087199834205259, "perr": 0.09, "d": 5, "type": "z", "time": "2024-07-16T12:15:42.993832"}
{"N": 72, "K": 12, "nTrials": 1000, "nBad": 668, "repairType": "A-X", "defectType": "singledefect", "defectLocation": [0], "ler": 0.08131956371343974, "perr": 0.1, "d": 5, "type": "z", "time": "2024-07-16T12:15:42.993832"}
{"N": 72, "K": 12, "nTrials": 1000, "nBad": 0, "repairType": "A-X", "defectType": "singledefect", "defectLocation": [0], "ler": 0.0, "perr": 0.01, "d": 50, "type": "x", "time": "2024-07-16T12:15:42.993832"}
{"N": 72, "K": 12, "nTrials": 1000, "nBad": 10, "repairType": "A-X", "defectType": "singledefect", "defectLocation": [0], "ler": 0.0007728039910219753, "perr": 0.02, "d": 5, "type": "x", "time": "2024-07-16T12:15:42.993832"}
{"N": 72, "K": 12, "nTrials": 1000, "nBad": 33, "repairType": "A-X", "defectType": "singledefect", "defectLocation": [0], "ler": 0.0025779623736639223, "perr": 0.03, "d": 5, "type": "x", "time": "2024-07-16T12:15:42.993832"}
{"N": 72, "K": 12, "nTrials": 1000, "nBad": 92, "repairType": "A-X", "defectType": "singledefect", "defectLocation": [0], "ler": 0.0073964262217510734, "perr": 0.04, "d": 5, "type": "x", "time": "2024-07-16T12:15:42.993832"}
{"N": 72, "K": 12, "nTrials": 1000, "nBad": 158, "repairType": "A-X", "defectType": "singledefect", "defectLocation": [0], "ler": 0.013141749639404954, "perr": 0.05, "d": 5, "type": "x", "time": "2024-07-16T12:15:42.993832"}
{"N": 72, "K": 12, "nTrials": 1000, "nBad": 255, "repairType": "A-X", "defectType": "singledefect", "defectLocation": [0], "ler": 0.022389478204537294, "perr": 0.06, "d": 5, "type": "x", "time": "2024-07-16T12:15:42.993832"}
{"N": 72, "K": 12, "nTrials": 1000, "nBad": 362, "repairType": "A-X", "defectType": "singledefect", "defectLocation": [0], "ler": 0.033979803971100675, "perr": 0.07, "d": 5, "type": "x", "time": "2024-07-16T12:15:42.993832"}
{"N": 72, "K": 12, "nTrials": 1000, "nBad": 467, "repairType": "A-X", "defectType": "singledefect", "defectLocation": [0], "ler": 0.04724987136775649, "perr": 0.08, "d": 5, "type": "x", "time": "2024-07-16T12:15:42.993832"}
{"N": 72, "K": 12, "nTrials": 1000, "nBad": 553, "repairType": "A-X", "defectType": "singledefect", "defectLocation": [0], "ler": 0.06005903275176461, "perr": 0.09, "d": 5, "type": "x", "time": "2024-07-16T12:15:42.993832"}
{"N": 72, "K": 12, "nTrials": 1000, "nBad": 679, "repairType": "A-X", "defectType": "singledefect", "defectLocation": [0], "ler": 0.08369754816889907, "perr": 0.1, "d": 5, "type": "x", "time": "2024-07-16T12:15:42.993832"}
{"N": 72, "K": 12, "nTrials": 1000, "nBad": 1, "repairType": "A-Z", "defectType": "singledefect", "defectLocation": [0], "ler": 7.695860265666266e-05, "perr": 0.01, "d": 6, "type": "z", "time": "2024-07-16T12:15:42.993832"}
{"N": 72, "K": 12, "nTrials": 1000, "nBad": 4, "repairType": "A-Z", "defectType": "singledefect", "defectLocation": [0], "ler": 0.00030826181583221146, "perr": 0.02, "d": 5, "type": "z", "time": "2024-07-16T12:15:42.993832"}
{"N": 72, "K": 12, "nTrials": 1000, "nBad": 29, "repairType": "A-Z", "defectType": "singledefect", "defectLocation": [0], "ler": 0.0022611943082979646, "perr": 0.03, "d": 5, "type": "z", "time": "2024-07-16T12:15:42.993832"}
{"N": 72, "K": 12, "nTrials": 1000, "nBad": 71, "repairType": "A-Z", "defectType": "singledefect", "defectLocation": [0], "ler": 0.005649101950261803, "perr": 0.04, "d": 5, "type": "z", "time": "2024-07-16T12:15:42.993832"}
{"N": 72, "K": 12, "nTrials": 1000, "nBad": 159, "repairType": "A-Z", "defectType": "singledefect", "defectLocation": [0], "ler": 0.013231956071379725, "perr": 0.05, "d": 5, "type": "z", "time": "2024-07-16T12:15:42.993832"}
{"N": 72, "K": 12, "nTrials": 1000, "nBad": 276, "repairType": "A-Z", "defectType": "singledefect", "defectLocation": [0], "ler": 0.02453731896336142, "perr": 0.06, "d": 5, "type": "z", "time": "2024-07-16T12:15:42.993832"}
{"N": 72, "K": 12, "nTrials": 1000, "nBad": 376, "repairType": "A-Z", "defectType": "singledefect", "defectLocation": [0], "ler": 0.035627164972817815, "perr": 0.07, "d": 5, "type": "z", "time": "2024-07-16T12:15:42.993832"}
{"N": 72, "K": 12, "nTrials": 1000, "nBad": 444, "repairType": "A-Z", "defectType": "singledefect", "defectLocation": [0], "ler": 0.044148626416029235, "perr": 0.08, "d": 5, "type": "z", "time": "2024-07-16T12:15:42.993832"}
{"N": 72, "K": 12, "nTrials": 1000, "nBad": 574, "repairType": "A-Z", "defectType": "singledefect", "defectLocation": [0], "ler": 0.06353177493754847, "perr": 0.09, "d": 5, "type": "z", "time": "2024-07-16T12:15:42.993832"}
{"N": 72, "K": 12, "nTrials": 1000, "nBad": 684, "repairType": "A-Z", "defectType": "singledefect", "defectLocation": [0], "ler": 0.08480341486948928, "perr": 0.1, "d": 5, "type": "z", "time": "2024-07-16T12:15:42.993832"}
{"N": 72, "K": 12, "nTrials": 1000, "nBad": 1, "repairType": "A-Z", "defectType": "singledefect", "defectLocation": [0], "ler": 7.695860265666266e-05, "perr": 0.01, "d": 6, "type": "x", "time": "2024-07-16T12:15:42.993832"}
{"N": 72, "K": 12, "nTrials": 1000, "nBad": 10, "repairType": "A-Z", "defectType": "singledefect", "defectLocation": [0], "ler": 0.0007728039910219753, "perr": 0.02, "d": 6, "type": "x", "time": "2024-07-16T12:15:42.993832"}
{"N": 72, "K": 12, "nTrials": 1000, "nBad": 43, "repairType": "A-Z", "defectType": "singledefect", "defectLocation": [0], "ler": 0.0033752055696757433, "perr": 0.03, "d": 5, "type": "x", "time": "2024-07-16T12:15:42.993832"}
{"N": 72, "K": 12, "nTrials": 1000, "nBad": 72, "repairType": "A-Z", "defectType": "singledefect", "defectLocation": [0], "ler": 0.005731477146483477, "perr": 0.04, "d": 5, "type": "x", "time": "2024-07-16T12:15:42.993832"}
{"N": 72, "K": 12, "nTrials": 1000, "nBad": 161, "repairType": "A-Z", "defectType": "singledefect", "defectLocation": [0], "ler": 0.013412666355655523, "perr": 0.05, "d": 5, "type": "x", "time": "2024-07-16T12:15:42.993832"}
{"N": 72, "K": 12, "nTrials": 1000, "nBad": 248, "repairType": "A-Z", "defectType": "singledefect", "defectLocation": [0], "ler": 0.0216859392662897, "perr": 0.06, "d": 5, "type": "x", "time": "2024-07-16T12:15:42.993832"}
{"N": 72, "K": 12, "nTrials": 1000, "nBad": 338, "repairType": "A-Z", "defectType": "singledefect", "defectLocation": [0], "ler": 0.03123186519954868, "perr": 0.07, "d": 5, "type": "x", "time": "2024-07-16T12:15:42.993832"}
{"N": 72, "K": 12, "nTrials": 1000, "nBad": 475, "repairType": "A-Z", "defectType": "singledefect", "defectLocation": [0], "ler": 0.048357580327785366, "perr": 0.08, "d": 5, "type": "x", "time": "2024-07-16T12:15:42.993832"}
{"N": 72, "K": 12, "nTrials": 1000, "nBad": 578, "repairType": "A-Z", "defectType": "singledefect", "defectLocation": [0], "ler": 0.06421111851897565, "perr": 0.09, "d": 5, "type": "x", "time": "2024-07-16T12:15:42.993832"}
{"N": 72, "K": 12, "nTrials": 1000, "nBad": 662, "repairType": "A-Z", "defectType": "singledefect", "defectLocation": [0], "ler": 0.08005296692968777, "perr": 0.1, "d": 5, "type": "x", "time": "2024-07-16T12:15:42.993832"}
{"N": 72, "K": 12, "nTrials": 1000, "nBad": 0, "repairType": "symmetry", "defectType": "singledefect", "defectLocation": [0], "ler": 0.0, "perr": 0.01, "d": 50, "type": "z", "time": "2024-07-16T12:15:42.993832"}
{"N": 72, "K": 12, "nTrials": 1000, "nBad": 6, "repairType": "symmetry", "defectType": "singledefect", "defectLocation": [0], "ler": 0.00046282150549747936, "perr": 0.02, "d": 5, "type": "z", "time": "2024-07-16T12:15:42.993832"}
{"N": 72, "K": 12, "nTrials": 1000, "nBad": 33, "repairType": "symmetry", "defectType": "singledefect", "defectLocation": [0], "ler": 0.0025779623736639223, "perr": 0.03, "d": 5, "type": "z", "time": "2024-07-16T12:15:42.993832"}
{"N": 72, "K": 12, "nTrials": 1000, "nBad": 79, "repairType": "symmetry", "defectType": "singledefect", "defectLocation": [0], "ler": 0.006310408497733899, "perr": 0.04, "d": 5, "type": "z", "time": "2024-07-16T12:15:42.993832"}
{"N": 72, "K": 12, "nTrials": 1000, "nBad": 168, "repairType": "symmetry", "defectType": "singledefect", "defectLocation": [0], "ler": 0.014048299257777064, "perr": 0.05, "d": 5, "type": "z", "time": "2024-07-16T12:15:42.993832"}
{"N": 72, "K": 12, "nTrials": 1000, "nBad": 251, "repairType": "symmetry", "defectType": "singledefect", "defectLocation": [0], "ler": 0.021986712587311663, "perr": 0.06, "d": 5, "type": "z", "time": "2024-07-16T12:15:42.993832"}
{"N": 72, "K": 12, "nTrials": 1000, "nBad": 369, "repairType": "symmetry", "defectType": "singledefect", "defectLocation": [0], "ler": 0.034799267073953755, "perr": 0.07, "d": 5, "type": "z", "time": "2024-07-16T12:15:42.993832"}
{"N": 72, "K": 12, "nTrials": 1000, "nBad": 484, "repairType": "symmetry", "defectType": "singledefect", "defectLocation": [0], "ler": 0.0496225328865052, "perr": 0.08, "d": 5, "type": "z", "time": "2024-07-16T12:15:42.993832"}
{"N": 72, "K": 12, "nTrials": 1000, "nBad": 554, "repairType": "symmetry", "defectType": "singledefect", "defectLocation": [0], "ler": 0.06022095202097821, "perr": 0.09, "d": 5, "type": "z", "time": "2024-07-16T12:15:42.993832"}
{"N": 72, "K": 12, "nTrials": 1000, "nBad": 668, "repairType": "symmetry", "defectType": "singledefect", "defectLocation": [0], "ler": 0.08131956371343974, "perr": 0.1, "d": 5, "type": "z", "time": "2024-07-16T12:15:42.993832"}
{"N": 72, "K": 12, "nTrials": 1000, "nBad": 2, "repairType": "symmetry", "defectType": "singledefect", "defectLocation": [0], "ler": 0.00015398834801338968, "perr": 0.01, "d": 6, "type": "x", "time": "2024-07-16T12:15:42.993832"}
{"N": 72, "K": 12, "nTrials": 1000, "nBad": 14, "repairType": "symmetry", "defectType": "singledefect", "defectLocation": [0], "ler": 0.0010839447515973433, "perr": 0.02, "d": 6, "type": "x", "time": "2024-07-16T12:15:42.993832"}
{"N": 72, "K": 12, "nTrials": 1000, "nBad": 30, "repairType": "symmetry", "defectType": "singledefect", "defectLocation": [0], "ler": 0.0023402732409635307, "perr": 0.03, "d": 5, "type": "x", "time": "2024-07-16T12:15:42.993832"}
{"N": 72, "K": 12, "nTrials": 1000, "nBad": 81, "repairType": "symmetry", "defectType": "singledefect", "defectLocation": [0], "ler": 0.0064765634982345555, "perr": 0.04, "d": 5, "type": "x", "time": "2024-07-16T12:15:42.993832"}
{"N": 72, "K": 12, "nTrials": 1000, "nBad": 146, "repairType": "symmetry", "defectType": "singledefect", "defectLocation": [0], "ler": 0.012066917948950429, "perr": 0.05, "d": 5, "type": "x", "time": "2024-07-16T12:15:42.993832"}
{"N": 72, "K": 12, "nTrials": 1000, "nBad": 259, "repairType": "symmetry", "defectType": "singledefect", "defectLocation": [0], "ler": 0.02279424494442628, "perr": 0.06, "d": 5, "type": "x", "time": "2024-07-16T12:15:42.993832"}
{"N": 72, "K": 12, "nTrials": 1000, "nBad": 356, "repairType": "symmetry", "defectType": "singledefect", "defectLocation": [0], "ler": 0.03328398605259286, "perr": 0.07, "d": 5, "type": "x", "time": "2024-07-16T12:15:42.993832"}
{"N": 72, "K": 12, "nTrials": 1000, "nBad": 481, "repairType": "symmetry", "defectType": "singledefect", "defectLocation": [0], "ler": 0.049198634530782326, "perr": 0.08, "d": 5, "type": "x", "time": "2024-07-16T12:15:42.993832"}
{"N": 72, "K": 12, "nTrials": 1000, "nBad": 594, "repairType": "symmetry", "defectType": "singledefect", "defectLocation": [0], "ler": 0.06698931376072625, "perr": 0.09, "d": 5, "type": "x", "time": "2024-07-16T12:15:42.993832"}
{"N": 72, "K": 12, "nTrials": 1000, "nBad": 660, "repairType": "symmetry", "defectType": "singledefect", "defectLocation": [0], "ler": 0.07963537742163362, "perr": 0.1, "d": 5, "type": "x", "time": "2024-07-16T12:15:42.993832"}
